rtl/core/counter_register.v
module CounterRegister #(parameter          N = 8)
						(input              clk, l,
						 input      [N-1:0] d,
						 output reg [N-1:0] q);

	initial q = 8'h00;

	always @ (posedge clk)
		if (l)
			q <= d;
		else
			q <= q + 1;

endmodule

rtl/peripherals/rom.sv
import defs::Instruction;

module Rom #(parameter 		    D = 16,
			 parameter		    A = 8)
	 		(input  		    clk,
	  		 input     [A-1:0]  addr,
	  		 output Instruction data_out);

	Instruction mem_array[2**A-1:0];

	initial $readmemh("bootloader/text.hex", mem_array);

	assign data_out = mem_array[addr];

endmodule

rtl/peripherals/ram.sv
import dmem::DMemCtrl;

module Ram #(
	parameter D = 8,
	parameter A = 8
) (
	input clk,
	DMemCtrl dmem_ctrl,
	output [D-1:0] data_out
);

	reg [D-1:0] mem_array[2**A-1:0];

	initial $readmemh("bootloader/data.hex", mem_array);

	assign data_out = mem_array[dmem_ctrl.addr];

	always @ (posedge clk) 
		if (dmem_ctrl.en)
			mem_array[dmem_ctrl.addr] <= dmem_ctrl.in;

endmodule

rtl/core/control_path.sv
import defs::*;
import ctrl::*;
import alu::AluCmd;

/*
typedef struct packed {
	// Selects destination register input, 0 = AluOut, 1 = Immediate
	logic dst_in_sel;
	// Enable write on destination register
	logic reg_wr_en;
	// Selects the operation in the alu
	AluCmd alu_cmd;

	logic dmem_en;
} CtrlSig;
*/

module ControlPath (
	input Opcode opcode,
	output CtrlSig ctrl_sig
);

	always_comb begin
		case (opcode)
			defs::ADD: ctrl_sig = '{0, 1, alu::ADD, 0};
			defs::NAND: ctrl_sig = '{0, 1, alu::NAND, 0};
			defs::SHFT: ctrl_sig = '{0, 1, alu::SHFT, 0};
			defs::INIT: ctrl_sig = '{1, 1, alu::DC, 0};
			defs::STOR: ctrl_sig = '{'x, 0, alu::DC, 1};
			//defs::LOAD: ctrl_sig = '{};
			default: ctrl_sig = 'x;
		endcase
	end

endmodule : ControlPath

rtl/core/alu.sv
import alu::*;

module Alu #(
	parameter D = 8
) (
	input [D-1:0]  a,
 	input [D-1:0]  b,
 	input Immed    n,
 	input AluCmd   cmd,
 	output logic [D-1:0] x
);

	always_comb begin
		case (cmd)
			ADD: assign x = a + b;
			NAND: assign x = ~(a & b);
			SHFT: assign x = n.flag ? a >> n.shamt : a << n.shamt;
			default: assign x = 'x;
		endcase
	end

endmodule : Alu

/* 
Decisão aberta para mudanças:
Coloquei a entrada do offset 'n' como um barramento separado da entrada b,
já que o n é um imediato de 4 bits enquanto o b é o conteúdo de um registrador
de 8 bits. Isso simplifica a necessidade de um mux externo, mas conta com um 
barramento adicional. De qualquer modo, pra implementar instruções como Fetch
e Send, será necessário multiplexar a entrada b do adder (ou adicionar outro
adder), afim de somar o conteúdo de um registrador a um imediato. 
Esse é um estudo que exige uma análise de temporização, consumo de 
área/energia e etc. que provavelmente terá resultados diferentes dependendo 
das outras funções implementadas nativamente para a Ula, portanto, creio que
deva ser mantido sobre supervisão.
*/

rtl/core/register_file.v
module RegisterFile #(parameter 	    D = 8,
					  parameter 	    I = 4)
					 (input				clk,
					  input			    wr_en,
					  input     [I-1:0] dst_id,
					  input	    [I-1:0] src1_id,
					  input	    [I-1:0] src2_id,
					  input	    [D-1:0] dst_in,
					  output    [D-1:0] src1_out,
					  output    [D-1:0] src2_out);

    reg [D-1:0] regarray[2**I-1:0];

    always @ (posedge clk)
    	if (wr_en) regarray[dst_id] <= dst_in;

	assign src1_out = (src1_id != 0) ? regarray[src1_id] : 0;
	assign src2_out = (src2_id != 0) ? regarray[src2_id] : 0;

endmodule

rtl/core/data_path.sv
import alu::*;
import ctrl::CtrlSig;

module DataPath (
	input clk,
	input [11:0] operands,
	input CtrlSig ctrl_sig,
	input [7:0] dmem_out,
	output DMemCtrl dmem_ctrl
);

	// rf
	logic wr_en;
	logic [3:0] dst_id;
	logic [3:0] src1_id;
	logic [3:0] src2_id;
	logic [7:0] dst_in;
	logic [7:0] src1_out;
	logic [7:0] src2_out;
	logic [7:0] imm;

	// ula
	logic [7:0] a;
 	logic [7:0] b;
 	Immed n;
	AluCmd cmd;
	logic [7:0] x;

	RegisterFile rf(.*);
	Alu alu (.*);


	
	// register file wirings
	assign wr_en = ctrl_sig.reg_wr_en;
	assign dst_id = operands[11:8];
	assign src1_id = operands[7:4];
	assign src2_id = operands[3:0];
	assign imm = operands[7:0];

	// ula wirings
 	assign n = operands[3:0];
 	assign cmd = ctrl_sig.alu_cmd;

 	assign a = src1_out;
 	assign b = src2_out;
 	assign dst_in = ctrl_sig.dst_in_sel ? imm : x;


endmodule

rtl/core/core.sv
import defs::*;
import ctrl::CtrlSig;
import dmem::DMemCtrl;

module BloodyRoot (
	input Instruction inst,
	input clk,

	input [7:0] dmem_out,
	output DMemCtrl dmem_ctrl
);

	Opcode opcode;
	logic [11:0] operands;
	CtrlSig ctrl_sig;

	DataPath dp (.*);
	ControlPath cp (.*);

	assign opcode = inst.opcode;
	assign operands = inst.operands;

endmodule : BloodyRoot

rtl/top.sv
module Top (input clk);
	import defs::Instruction;
	import dmem::DMemCtrl;

	Instruction inst;
	logic load = 0;
	logic [7:0] ip_data = 'x;
	logic [7:0] imem_addr;
	DMemCtrl dmem_ctrl;
	logic [7:0] dmem_out;

	BloodyRoot br (.*);
	Ram dmem (
		.clk(clk),
		.dmem_ctrl(dmem_ctrl),
		.data_out(dmem_out)
	);
	Rom imem (
		.clk(clk),
		.addr(imem_addr),
		.data_out(inst)
	);
	CounterRegister ip (
		.clk(clk),
		.l(load),
		.d(ip_data),
		.q(imem_addr)
	);


endmodule : Top

obj_dir/waves/system.vcd
$version Generated by VerilatedVcd $end
$timescale 1ps $end
 $scope module TOP $end
  $var wire 1 C clk $end
  $scope module Top $end
   $var wire 1 C clk $end
   $var wire 16 # inst [15:0] $end
   $var wire 1 D load $end
   $var wire 8 E ip_data [7:0] $end
   $var wire 8 $ imem_addr [7:0] $end
   $var wire 17 F dmem_ctrl [16:0] $end
   $var wire 8 % dmem_out [7:0] $end
   $scope module br $end
    $var wire 16 # inst [15:0] $end
    $var wire 1 C clk $end
    $var wire 8 % dmem_out [7:0] $end
    $var wire 17 F dmem_ctrl [16:0] $end
    $var wire 4 & opcode [3:0] $end
    $var wire 12 ' operands [11:0] $end
    $var wire 5 ( ctrl_sig [4:0] $end
    $scope module cp $end
     $var wire 4 & opcode [3:0] $end
     $var wire 5 ( ctrl_sig [4:0] $end
    $upscope $end
    $scope module dp $end
     $var wire 1 C clk $end
     $var wire 12 ' operands [11:0] $end
     $var wire 5 ( ctrl_sig [4:0] $end
     $var wire 8 % dmem_out [7:0] $end
     $var wire 17 F dmem_ctrl [16:0] $end
     $var wire 1 ) wr_en $end
     $var wire 4 * dst_id [3:0] $end
     $var wire 4 + src1_id [3:0] $end
     $var wire 4 , src2_id [3:0] $end
     $var wire 8 - dst_in [7:0] $end
     $var wire 8 . src1_out [7:0] $end
     $var wire 8 / src2_out [7:0] $end
     $var wire 8 0 imm [7:0] $end
     $var wire 8 . a [7:0] $end
     $var wire 8 / b [7:0] $end
     $var wire 4 , n [3:0] $end
     $var wire 2 1 cmd [1:0] $end
     $var wire 8 2 x [7:0] $end
     $scope module alu $end
      $var wire 32 G D [31:0] $end
      $var wire 8 . a [7:0] $end
      $var wire 8 / b [7:0] $end
      $var wire 4 , n [3:0] $end
      $var wire 2 1 cmd [1:0] $end
      $var wire 8 2 x [7:0] $end
     $upscope $end
     $scope module rf $end
      $var wire 32 G D [31:0] $end
      $var wire 32 H I [31:0] $end
      $var wire 1 C clk $end
      $var wire 1 ) wr_en $end
      $var wire 4 * dst_id [3:0] $end
      $var wire 4 + src1_id [3:0] $end
      $var wire 4 , src2_id [3:0] $end
      $var wire 8 - dst_in [7:0] $end
      $var wire 8 . src1_out [7:0] $end
      $var wire 8 / src2_out [7:0] $end
      $var wire 8 3 regarray[0] [7:0] $end
      $var wire 8 4 regarray[1] [7:0] $end
      $var wire 8 5 regarray[2] [7:0] $end
      $var wire 8 6 regarray[3] [7:0] $end
      $var wire 8 7 regarray[4] [7:0] $end
      $var wire 8 8 regarray[5] [7:0] $end
      $var wire 8 9 regarray[6] [7:0] $end
      $var wire 8 : regarray[7] [7:0] $end
      $var wire 8 ; regarray[8] [7:0] $end
      $var wire 8 < regarray[9] [7:0] $end
      $var wire 8 = regarray[10] [7:0] $end
      $var wire 8 > regarray[11] [7:0] $end
      $var wire 8 ? regarray[12] [7:0] $end
      $var wire 8 @ regarray[13] [7:0] $end
      $var wire 8 A regarray[14] [7:0] $end
      $var wire 8 B regarray[15] [7:0] $end
     $upscope $end
    $upscope $end
   $upscope $end
   $scope module dmem $end
    $var wire 32 G D [31:0] $end
    $var wire 32 G A [31:0] $end
    $var wire 1 C clk $end
    $var wire 17 F dmem_ctrl [16:0] $end
    $var wire 8 % data_out [7:0] $end
   $upscope $end
   $scope module imem $end
    $var wire 32 I D [31:0] $end
    $var wire 32 G A [31:0] $end
    $var wire 1 C clk $end
    $var wire 8 $ addr [7:0] $end
    $var wire 16 # data_out [15:0] $end
   $upscope $end
   $scope module ip $end
    $var wire 32 G N [31:0] $end
    $var wire 1 C clk $end
    $var wire 1 D l $end
    $var wire 8 E d [7:0] $end
    $var wire 8 $ q [7:0] $end
   $upscope $end
  $upscope $end
 $upscope $end
$enddefinitions $end


#0
b1010000100001010 #
b00000000 $
b00000000 %
b1010 &
b000100001010 '
b11000 (
1)
b0001 *
b0000 +
b1010 ,
b00001010 -
b00000000 .
b00000000 /
b00001010 0
b00 1
b00000000 2
b00000000 3
b00000000 4
b00000000 5
b00000000 6
b00000000 7
b00000000 8
b00000000 9
b00000000 :
b00000000 ;
b00000000 <
b00000000 =
b00000000 >
b00000000 ?
b00000000 @
b00000000 A
b00000000 B
1C
0D
b00000000 E
b00000000000000000 F
b00000000000000000000000000001000 G
b00000000000000000000000000000100 H
b00000000000000000000000000010000 I
#1
0C
#2
b1010001000000011 #
b00000001 $
b001000000011 '
b0010 *
b0011 ,
b00000011 -
b00000011 0
b00001010 4
1C
#3
0C
#4
b0000001100000001 #
b00000010 $
b0000 &
b001100000001 '
b01000 (
b0011 *
b0001 ,
b00001010 -
b00001010 /
b00000001 0
b00001010 2
b00000011 5
1C
#5
0C
#6
b0000001100110010 #
b00000011 $
b001100110010 '
b0011 +
b0010 ,
b00001101 -
b00001010 .
b00000011 /
b00110010 0
b00001101 2
b00001010 6
1C
#7
0C
#8
b1100000100000000 #
b00000100 $
b1100 &
b000100000000 '
b00001 (
0)
b0001 *
b0000 +
b0000 ,
b00000000 -
b00000000 .
b00000000 /
b00000000 0
b00000000 2
b00001101 6
1C
#9
0C
#10
b1100001000000001 #
b00000101 $
b001000000001 '
b0010 *
b0001 ,
b00001010 -
b00001010 /
b00000001 0
b00001010 2
1C
#11
0C
#12
b1100001100000010 #
b00000110 $
b001100000010 '
b0011 *
b0010 ,
b00000011 -
b00000011 /
b00000010 0
b00000011 2
1C
#13
0C
#14
b0000000000000000 #
b00000111 $
b0000 &
b000000000000 '
b01000 (
1)
b0000 *
b0000 ,
b00000000 -
b00000000 /
b00000000 0
b00000000 2
1C
#15
0C
#16
b00001000 $
1C
#17
0C
#18
b00001001 $
1C
#19
0C
#20
b00001010 $
1C
#21
0C
#22
b00001011 $
1C
#23
0C
#24
b00001100 $
1C
#25
0C
#26
b00001101 $
1C
#27
0C
#28
b00001110 $
1C
